molint/.eslintrc.js
molint/.pylintrc
molint/README.md
molint/__init__.py
molint/scan.py
molint-1.0.9.dist-info/METADATA
molint-1.0.9.dist-info/WHEEL
molint-1.0.9.dist-info/entry_points.txt
molint-1.0.9.dist-info/top_level.txt
molint-1.0.9.dist-info/RECORD
