Metadata-Version: 2.1
Name: molint
Version: 1.0.9
Summary: 扫描py文件
Home-page: UNKNOWN
Author: mzg
License: UNKNOWN
Platform: UNKNOWN
Requires-Dist: pylint (==2.9.5)
